humanreadable/__init__.py
humanreadable/__version__.py
humanreadable/_base.py
humanreadable/_common.py
humanreadable/_const.py
humanreadable/_persec.py
humanreadable/_time.py
humanreadable/_types.py
humanreadable/_typing.py
humanreadable/error.py
humanreadable/py.typed
humanreadable-0.4.0.dist-info/LICENSE
humanreadable-0.4.0.dist-info/METADATA
humanreadable-0.4.0.dist-info/WHEEL
humanreadable-0.4.0.dist-info/top_level.txt
humanreadable-0.4.0.dist-info/RECORD
